[
    {
      "name": "Arroz 100% Grãos Nobres - 2kg",
      "description": "Arroz; arroz 2kg; arroz branco; arroz nobre; Tio Joao; Tio João; Almoço; Jantar; Refeição; arroz tio joao",
      "image": "https://m.media-amazon.com/images/I/61OYxSAwPIL._AC_SL1000_.jpg",
      "price": 15.99
    },
    {
      "name": "Feijão Moyashi Viva Salute Embalado a Vácuo - 1Kg",
      "description": "",
      "image": "https://m.media-amazon.com/images/I/61J7FCBDnGL._AC_SL1000_.jpg",
      "price": 29.00
    },
      
      {
        "name": "Piracanjuba - Leite Condensado Semidesnatado, 395g",
        "description": "O Produto Entrega Qualidade, Sabor E O Ponto Ideal Para Qualquer Preparação",
        "image": "https://m.media-amazon.com/images/I/51Oujf6RDtL._AC_SL1000_.jpg",
        "price": 9.99
      },
      {
        "name": "Bebida à Base de Castanha-De-Caju Orgânica Leite Possible Caixa 1L",
        "description": "O Produto Entrega Qualidade, Sabor E O Ponto Ideal Para Qualquer Preparação",
        "image": "https://m.media-amazon.com/images/I/51l8YOpDgUL._AC_SL1000_.jpg",
        "price": 15.00
      },
      {
        "name": "Macarrão Massa Tortiglioni Tortilhone com Ovos Germani 500G",
        "description": "O Tortilhone com Ovos Germani tem forma de canudo retorcido. É perfeito para acomodar molhos cremosos ou fluídos, que entram pelo seu orifício e perpassam a massa por meio de suas ranhuras, ressaltando o sabor dos condimentos.",
        "image": "https://m.media-amazon.com/images/I/613LPcRvHfL._AC_SL1200_.jpg",
        "price": 14.40
      },
      {
        "name": "Batata Palha 500g Marpa Sequinha e Crocante",
        "description": "Snack, acompanhamento",
        "image": "https://m.media-amazon.com/images/I/61xIe9-jmVL._AC_SL1200_.jpg",
        "price": 21.90
      }
   
  ]